telegram_export_explorer/__init__.py
telegram_export_explorer/build_db.py
telegram_export_explorer/datatypes.py
telegram_export_explorer/db.py
telegram_export_explorer/exceptions.py
telegram_export_explorer/message_matchers.py
telegram_export_explorer/tag_utils.py
telegram_export_explorer/utils.py
telegram_export_explorer-0.0.4.dist-info/METADATA
telegram_export_explorer-0.0.4.dist-info/WHEEL
telegram_export_explorer-0.0.4.dist-info/entry_points.txt
telegram_export_explorer-0.0.4.dist-info/licenses/LICENSE
telegram_export_explorer-0.0.4.dist-info/RECORD
