Metadata-Version: 2.4
Name: telegram-export-explorer
Version: 0.0.4
Summary: A tool for parsing and exploring exported Telegram conversations
Project-URL: Homepage, https://codeberg.org/whispered-good/telegram-export-explorer
Project-URL: Issues, https://codeberg.org/whispered-good/telegram-export-explorer/issues
Project-URL: Repository, https://codeberg.org/whispered-good/telegram-export-explorer.git
Author-email: Whispered Good <whispered-good@pm.me>
License-Expression: MIT
License-File: LICENSE
Keywords: telegram
Classifier: Development Status :: 3 - Alpha
Classifier: Operating System :: OS Independent
Classifier: Programming Language :: Python :: 3
Requires-Python: >=3.8
Requires-Dist: beautifulsoup4
Provides-Extra: dev
Requires-Dist: black; extra == 'dev'
Requires-Dist: build; extra == 'dev'
Requires-Dist: flake8; extra == 'dev'
Requires-Dist: mypy; extra == 'dev'
Requires-Dist: pylint; extra == 'dev'
Requires-Dist: twine; extra == 'dev'
Requires-Dist: types-beautifulsoup4; extra == 'dev'
